oe_utils/__init__.py
oe_utils/audit.py
oe_utils/range_parser.py
oe_utils/data/__init__.py
oe_utils/data/data_managers.py
oe_utils/data/data_transfer_objects.py
oe_utils/data/data_types.py
oe_utils/data/db_audit_manager.py
oe_utils/data/models/__init__.py
oe_utils/data/models/meta.py
oe_utils/data/models/models.py
oe_utils/deploy/__init__.py
oe_utils/document/__init__.py
oe_utils/document/documentengine.py
oe_utils/email/__init__.py
oe_utils/email/smtp.py
oe_utils/jobs/__init__.py
oe_utils/qr/__init__.py
oe_utils/qr/pdf.py
oe_utils/scripts/__init__.py
oe_utils/scripts/archive_feed.py
oe_utils/search/__init__.py
oe_utils/search/indexer.py
oe_utils/search/query_builder.py
oe_utils/search/searchengine.py
oe_utils/utils/__init__.py
oe_utils/utils/actor_utils.py
oe_utils/utils/file_utils.py
oe_utils/utils/json_utils.py
oe_utils/validation/__init__.py
oe_utils/validation/validators.py
oe_utils/validation/validators_actor.py
oe_utils/views/__init__.py
oe_utils/views/atom.py
oe_utils/views/exceptions.py
oe_utils-1.8.0.dist-info/LICENSE
oe_utils-1.8.0.dist-info/METADATA
oe_utils-1.8.0.dist-info/WHEEL
oe_utils-1.8.0.dist-info/top_level.txt
oe_utils-1.8.0.dist-info/RECORD
