Metadata-Version: 2.1
Name: oe-utils
Version: 1.8.0
Summary: Utility Library
Home-page: https://github.com/OnroerendErfgoed/oe_utils
Author: Flanders Heritage Agency
Author-email: ict@onroerenderfgoed.be
License: MIT
Keywords: oe utility
Platform: UNKNOWN
Classifier: Development Status :: 3 - Alpha
Classifier: Intended Audience :: Developers
Classifier: Topic :: Utilities
Classifier: License :: OSI Approved :: MIT License
Classifier: Programming Language :: Python :: 2
Classifier: Programming Language :: Python :: 2.7
Classifier: Programming Language :: Python :: 3
Classifier: Programming Language :: Python :: 3.4
Classifier: Programming Language :: Python :: 3.5
Requires-Dist: requests
Requires-Dist: PyYAML
Requires-Dist: feedgen (>=0.9.0)
Requires-Dist: simplejson
Requires-Dist: future
Requires-Dist: python-stdnum
Requires-Dist: pytz
Requires-Dist: zope.interface
Requires-Dist: Deprecated
Provides-Extra: all
Requires-Dist: pyramid ; extra == 'all'
Requires-Dist: colander (>=1.7.0) ; extra == 'all'
Requires-Dist: cornice (>=3.6.0) ; extra == 'all'
Requires-Dist: rfc3987 ; extra == 'all'
Requires-Dist: rq ; extra == 'all'
Requires-Dist: sqlalchemy ; extra == 'all'
Requires-Dist: reportlab (==3.5.12) ; extra == 'all'
Provides-Extra: db
Requires-Dist: sqlalchemy ; extra == 'db'
Provides-Extra: qr
Requires-Dist: reportlab (==3.5.12) ; extra == 'qr'
Provides-Extra: redis
Requires-Dist: rq ; extra == 'redis'
Provides-Extra: web
Requires-Dist: pyramid ; extra == 'web'
Requires-Dist: colander (>=1.7.0) ; extra == 'web'
Requires-Dist: cornice (>=3.6.0) ; extra == 'web'
Requires-Dist: rfc3987 ; extra == 'web'
